vivid/db/__init__.py
vivid_db-0.1.11.dist-info/LICENSE
vivid_db-0.1.11.dist-info/METADATA
vivid_db-0.1.11.dist-info/WHEEL
vivid_db-0.1.11.dist-info/top_level.txt
vivid_db-0.1.11.dist-info/zip-safe
vivid_db-0.1.11.dist-info/RECORD
