Metadata-Version: 2.1
Name: vivid-db
Version: 0.1.11
Summary: Universal Data Mapper
Home-page: https://www.frootlab.org/deet
Author: Frootlab Developers
Author-email: contact@frootlab.org
License: GPLv3
Keywords: database database-proxy orm-framework data-warehouse
Platform: UNKNOWN
Classifier: Development Status :: 2 - Pre-Alpha
Classifier: Intended Audience :: Science/Research
Classifier: License :: OSI Approved :: GNU General Public License v3 (GPLv3)
Classifier: Programming Language :: Python :: 3
Classifier: Programming Language :: Python :: 3.7
Classifier: Operating System :: OS Independent
Classifier: Topic :: Scientific/Engineering :: Artificial Intelligence
Classifier: Topic :: Scientific/Engineering :: Information Analysis
Classifier: Topic :: Database :: Database Engines/Servers
Classifier: Topic :: Software Development :: Libraries :: Python Modules
Requires-Python: >=3.7
Requires-Dist: deet (>=0.1.11)
